agent_kernel/__init__.py
agent_kernel/analyzer.py
agent_kernel/auditor.py
agent_kernel/completeness_auditor.py
agent_kernel/detector.py
agent_kernel/kernel.py
agent_kernel/memory_manager.py
agent_kernel/models.py
agent_kernel/nudge_mechanism.py
agent_kernel/outcome_analyzer.py
agent_kernel/patcher.py
agent_kernel/semantic_analyzer.py
agent_kernel/semantic_purge.py
agent_kernel/simulator.py
agent_kernel/teacher.py
agent_kernel/triage.py
src/__init__.py
src/agents/__init__.py
src/agents/conflict_resolution.py
src/agents/orchestrator.py
src/agents/pubsub.py
src/agents/shadow_teacher.py
src/agents/swarm.py
src/agents/worker.py
src/integrations/__init__.py
src/integrations/cmvk_adapter.py
src/integrations/control_plane_adapter.py
src/integrations/langchain_integration.py
src/interfaces/__init__.py
src/interfaces/llm_clients.py
src/interfaces/openapi_tools.py
src/interfaces/plugin_system.py
src/interfaces/protocols.py
src/interfaces/telemetry.py
src/interfaces/tool_registry.py
src/kernel/__init__.py
src/kernel/auditor.py
src/kernel/circuit_breaker.py
src/kernel/core.py
src/kernel/distributed.py
src/kernel/evolution.py
src/kernel/failover.py
src/kernel/governance.py
src/kernel/governance_v2.py
src/kernel/lazy_evaluator.py
src/kernel/load_testing.py
src/kernel/memory.py
src/kernel/patcher.py
src/kernel/rubric.py
src/kernel/schemas.py
src/kernel/skill_mapper.py
src/kernel/triage.py
src/mocks/__init__.py
scak-2.1.0.dist-info/METADATA
scak-2.1.0.dist-info/WHEEL
scak-2.1.0.dist-info/entry_points.txt
scak-2.1.0.dist-info/top_level.txt
scak-2.1.0.dist-info/RECORD
