Metadata-Version: 2.4
Name: scak
Version: 2.1.0
Summary: Self-Correcting Agent Kernel: A specialized extension for Control Plane that implements Laziness Detection and Self-Correction loops using CMVK
Home-page: https://github.com/imran-siddique/self-correcting-agent-kernel
Author: Self-Correcting Agent Team
Author-email: research@scak.ai
License: MIT
Project-URL: Bug Tracker, https://github.com/imran-siddique/self-correcting-agent-kernel/issues
Project-URL: Documentation, https://github.com/imran-siddique/self-correcting-agent-kernel/wiki
Project-URL: Source Code, https://github.com/imran-siddique/self-correcting-agent-kernel
Project-URL: Changelog, https://github.com/imran-siddique/self-correcting-agent-kernel/blob/main/CHANGELOG.md
Keywords: ai agents self-correction alignment differential-auditing semantic-purge llm production-ml scak control-plane cmvk laziness-detection
Classifier: Development Status :: 4 - Beta
Classifier: Intended Audience :: Developers
Classifier: Intended Audience :: Science/Research
Classifier: License :: OSI Approved :: MIT License
Classifier: Operating System :: OS Independent
Classifier: Programming Language :: Python :: 3
Classifier: Programming Language :: Python :: 3.9
Classifier: Programming Language :: Python :: 3.10
Classifier: Programming Language :: Python :: 3.11
Classifier: Programming Language :: Python :: 3.12
Classifier: Topic :: Scientific/Engineering :: Artificial Intelligence
Classifier: Topic :: Software Development :: Libraries :: Python Modules
Classifier: Framework :: AsyncIO
Requires-Python: >=3.9
Requires-Dist: pydantic>=2.0.0
Requires-Dist: pyyaml>=6.0
Requires-Dist: agent-primitives>=0.1.0
Provides-Extra: control-plane
Requires-Dist: agent-control-plane>=1.0.0; extra == "control-plane"
Provides-Extra: cmvk
Requires-Dist: cmvk>=1.0.0; extra == "cmvk"
Provides-Extra: full
Requires-Dist: agent-control-plane>=1.0.0; extra == "full"
Requires-Dist: cmvk>=1.0.0; extra == "full"
Provides-Extra: llm
Requires-Dist: openai>=1.0.0; extra == "llm"
Requires-Dist: anthropic>=0.7.0; extra == "llm"
Provides-Extra: dev
Requires-Dist: pytest>=7.4.0; extra == "dev"
Requires-Dist: pytest-asyncio>=0.21.0; extra == "dev"
Requires-Dist: streamlit>=1.28.0; extra == "dev"
Requires-Dist: jupyter>=1.0.0; extra == "dev"
Provides-Extra: all
Requires-Dist: agent-control-plane>=1.0.0; extra == "all"
Requires-Dist: cmvk>=1.0.0; extra == "all"
Requires-Dist: openai>=1.0.0; extra == "all"
Requires-Dist: anthropic>=0.7.0; extra == "all"
Requires-Dist: pytest>=7.4.0; extra == "all"
Requires-Dist: pytest-asyncio>=0.21.0; extra == "all"
Requires-Dist: streamlit>=1.28.0; extra == "all"
Requires-Dist: jupyter>=1.0.0; extra == "all"
Dynamic: author
Dynamic: author-email
Dynamic: classifier
Dynamic: description
Dynamic: description-content-type
Dynamic: home-page
Dynamic: keywords
Dynamic: license
Dynamic: project-url
Dynamic: provides-extra
Dynamic: requires-dist
Dynamic: requires-python
Dynamic: summary
